{"gerber_cutoutgapsize": 0.15, "gerber_noncopperrounded": false, "geometry_paintoverlap": 0.15, "excellon_plot": true, "gerber_isotooldia": 0.016, "gerber_plot": true, "excellon_drillz": -0.1, "geometry_feedrate": 3.0, "units": "IN", "excellon_travelz": 0.1, "gerber_multicolored": false, "gerber_solid": true, "gerber_isopasses": 1, "cncjob_append": "", "excellon_feedrate": 3.0, "cncjob_tooldia": 0.016, "geometry_travelz": 0.1, "gerber_cutoutmargin": 0.1, "excellon_solid": true, "geometry_paintmargin": 0.0, "geometry_cutz": -0.002, "gerber_noncoppermargin": 0.0, "gerber_cutouttooldia": 0.07, "gerber_gaps": "4", "gerber_bboxmargin": 0.0, "cncjob_plot": true, "geometry_plot": true, "gerber_isooverlap": 0.15, "gerber_bboxrounded": false, "geometry_cnctooldia": 0.016, "geometry_painttooldia": 0.07}